[
  {
    "@context": "https://schema.org",
    "@type": "WebPage",
    "name": "東國大學的真相：種族化性暴力時間線",
    "description": "互動時間線記錄東國大學十年間種族化性暴力事件、制度性失職及公款詐欺指控（2008-2025）。",
    "url": "https://genderwatchdog1.github.io/timeline-website/timeline_zh_tw.html",
    "datePublished": "2025-04-05T12:00:00+09:00",
    "dateModified": "2025-05-15T12:00:00+09:00",
    "author": {
      "@type": "Organization",
      "name": "Gender Watchdog"
    },
    "mainEntity": {
      "@type": "ItemList",
      "name": "東國大學種族化性暴力時間線",
      "description": "按時間順序記錄東國大學2008-2025年間種族化性暴力事件、制度性失敗和倡議努力",
      "numberOfItems": 16,
      "itemListOrder": "Ascending",
      "itemListElement": [
        {
          "@type": "Event",
          "name": "申姬門醜聞",
          "startDate": "2008",
          "description": "涉及機構虛假陳述的重大醜聞。該大學利用美國法律而忽視其價值觀。",
          "location": {
            "@type": "Organization",
            "name": "東國大學"
          },
          "url": "https://genderwatchdog1.github.io/timeline-website/blog_posts/zh_tw/shingate.html"
        },
        {
          "@type": "Event",
          "name": "媒體傳播學教授性暴力事件",
          "startDate": "2015-11",
          "description": "教授在飲酒聚會期間對東國大學研究生實施性暴力。",
          "location": {
            "@type": "Organization",
            "name": "東國大學"
          },
          "url": "https://genderwatchdog1.github.io/timeline-website/blog_posts/zh_tw/2016_dongguk_prof_sexual_assault.html",
          "keywords": "性暴力, 教授不當行為, 種族化性暴力"
        },
        {
          "@type": "Event",
          "name": "媒體傳播學教授性暴力事件通知大學",
          "startDate": "2016-02",
          "description": "東國大學媒體傳播專業教授因對女研究生實施性暴力被起訴。大學顯示延遲回應和被動處理方式。",
          "location": {
            "@type": "Organization",
            "name": "東國大學"
          },
          "url": "https://genderwatchdog1.github.io/timeline-website/blog_posts/zh_tw/2016_dongguk_prof_sexual_assault.html",
          "keywords": "性暴力起訴, 制度性疏忽"
        },
        {
          "@type": "Event",
          "name": "教授更換政策",
          "startDate": "2016-08",
          "description": "東國大學引入條款，允許受到言語虐待或性暴力的學生申請更換教授。",
          "location": {
            "@type": "Organization",
            "name": "東國大學"
          },
          "url": "https://genderwatchdog1.github.io/timeline-website/blog_posts/zh_tw/dongguk_exposed_2016_2025.html#1-2016-professor-replacement-policy",
          "keywords": "政策改革, 性暴力防治"
        },
        {
          "@type": "Event",
          "name": "女學生會被解散",
          "startDate": "2018",
          "description": "在MeToo運動達到高潮時，東國大學解散了女學生會這一重要女性倡導團體。",
          "location": {
            "@type": "Organization",
            "name": "東國大學"
          },
          "url": "https://genderwatchdog1.github.io/timeline-website/blog_posts/zh_tw/dongguk_exposed_2016_2025.html#2-2018-metoo-movement-abolition-of-the-womens-student-council",
          "keywords": "制度性倒退, 女性倡議消除"
        },
        {
          "@type": "Event",
          "name": "KWDI藝術領域性暴力報告",
          "startDate": "2020",
          "description": "韓國女性發展研究院發布關於藝術教育項目中性暴力的全面報告，強調包括東國大學在內的系統性問題。",
          "location": {
            "@type": "Country",
            "name": "韓國"
          },
          "url": "https://genderwatchdog1.github.io/timeline-website/blog_posts/zh_tw/kwdi_infographics.html",
          "keywords": "研究文檔, 性暴力統計"
        },
        {
          "@type": "Event",
          "name": "初始電子郵件聯繫",
          "startDate": "2025-03-08",
          "endDate": "2025-03-09",
          "description": "關於性暴力問題的初始電子郵件發送給東國大學但未收到回應，開始機構沉默模式。",
          "location": {
            "@type": "Organization",
            "name": "東國大學"
          },
          "keywords": "倡議聯繫, 制度性沉默"
        },
        {
          "@type": "Event",
          "name": "聯繫所有教授",
          "startDate": "2025-03-14",
          "endDate": "2025-03-15",
          "description": "聯繫東國大學數位內容與媒體研究生院所有教授，但完全沒有回應，顯示集體性機構沉默。",
          "location": {
            "@type": "Organization",
            "name": "東國大學"
          },
          "keywords": "教授聯繫, 集體沉默"
        },
        {
          "@type": "Event",
          "name": "部落格發布：東國大學真相",
          "startDate": "2025-04-05",
          "description": "Gender Watchdog部落格發布虛假合作關係聲明證據和十年性暴力事件及制度性疏忽的模式。",
          "location": {
            "@type": "Organization",
            "name": "東國大學"
          },
          "url": "https://genderwatchdog1.github.io/timeline-website/blog_posts/zh_tw/dongguk_exposed_2016_2025.html",
          "keywords": "調查文檔, 合作關係詐欺, 種族化性暴力"
        },
        {
          "@type": "Event",
          "name": "Title IX風險升級",
          "startDate": "2025-04-05",
          "endDate": "2025-04-06",
          "description": "東國大學對Title IX風險問題無禮回應「您的電子郵件目的是什麼？」，顯示未能有意義回應安全問題。",
          "location": {
            "@type": "Organization",
            "name": "東國大學"
          },
          "url": "https://genderwatchdog1.github.io/timeline-website/blog_posts/zh_tw/title_ix_risk_advisory.html",
          "keywords": "Title IX違規, 制度性無禮"
        },
        {
          "@type": "Event",
          "name": "合作大學回應",
          "startDate": "2025-04-07",
          "description": "被東國大學列為合作夥伴的多所大學開始回應，加拿大機構表示「我們學校與東國大學沒有學生交流協議」。",
          "location": {
            "@type": "Place",
            "name": "國際"
          },
          "url": "https://genderwatchdog1.github.io/timeline-website/blog_posts/zh_tw/fictional_partnerships_title_ix_dongguk.html",
          "keywords": "合作關係驗證, 制度性詐欺"
        },
        {
          "@type": "Event",
          "name": "大學沉默持續",
          "startDate": "2025-04-06",
          "description": "自4月5-6日電子郵件後，東國大學拒絕進一步溝通，加深對該機構解決種族化性暴力風險承諾的擔憂。",
          "location": {
            "@type": "Organization",
            "name": "東國大學"
          },
          "keywords": "制度性沉默, 問責逃避"
        },
        {
          "@type": "Event",
          "name": "部落格揭露：虛假合作與涉嫌納稅人詐欺",
          "startDate": "2025-05-02",
          "description": "Gender Watchdog發布確鑿證據，證明東國大學繼續虛假聲稱與已正式否認關係的大學存在合作，引發納稅人詐欺問題。",
          "location": {
            "@type": "Organization",
            "name": "東國大學"
          },
          "url": "https://genderwatchdog1.github.io/timeline-website/blog_posts/zh_tw/false_partners_alleged_taxpayer_fraud.html",
          "keywords": "納稅人詐欺, 虛假合作關係, 制度性欺騙"
        },
        {
          "@type": "Event",
          "name": "25天政府沉默",
          "startDate": "2025-05-04",
          "description": "收到合作關係詐欺證據後，七個韓國政府機構完全沉默25天，直接強化了助長種族化性暴力的結構性條件。",
          "location": {
            "@type": "Country",
            "name": "韓國"
          },
          "url": "https://genderwatchdog1.github.io/timeline-website/blog_posts/zh_tw/05102025_korean_govt_slow.html",
          "keywords": "政府疏忽, 系統性助長"
        },
        {
          "@type": "Event",
          "name": "IEQAS認證危機揭露",
          "startDate": "2025-05-12",
          "description": "調查擴展至韓國高等教育系統性種族化性暴力問題，揭露受損的IEQAS認證和助長針對外籍女性的全男性教師組成。",
          "location": {
            "@type": "Country",
            "name": "韓國"
          },
          "url": "https://genderwatchdog1.github.io/timeline-website/blog_posts/zh_tw/05152025_zh_tw_horizontal_ieqas.html",
          "keywords": "系統性調查, IEQAS認證, 種族化針對"
        }
      ]
    }
  },
  {
    "@context": "https://schema.org",
    "@type": "Organization",
    "name": "Gender Watchdog",
    "url": "https://genderwatchdog1.github.io/timeline-website/",
    "logo": "https://genderwatchdog1.github.io/timeline-website/imgs/favicons/gender_watchdog_favicon_128x128.png",
    "description": "記錄和對抗韓國大學和影視產業中的種族化性暴力。要求學術界和產業界承擔責任。",
    "sameAs": [
      "https://x.com/Gender_Watchdog",
      "https://blog.genderwatchdog.org/",
      "https://metookorea2025.genderwatchdog.org/",
      "https://www.youtube.com/@GenderWatchdog"
    ],
    "contactPoint": {
      "@type": "ContactPoint",
      "contactType": "advocacy"
    }
  },
  {
    "@context": "https://schema.org",
    "@type": "FAQPage",
    "mainEntity": [
      {
        "@type": "Question",
        "name": "這個時間線記錄了什麼？",
        "acceptedAnswer": {
          "@type": "Answer",
          "text": "這個互動時間線記錄了東國大學2008-2025年間十年的種族化性暴力事件、制度性疏忽和涉嫌公款詐欺。每個時間線事件都連結到詳細文檔，提供系統性針對外籍女性（特別是來自中國和東南亞）的證據以及制度性回應失敗。"
        }
      },
      {
        "@type": "Question",
        "name": "如何獲取每個時間線事件的詳細信息？",
        "acceptedAnswer": {
          "@type": "Answer",
          "text": "點擊任何時間線事件即可獲取包含證據、分析和多語言內容的全面部落格文章文檔。每個事件都包含完整文章的連結，提供繁體中文、英文、韓文、日文和簡體中文版本。"
        }
      },
      {
        "@type": "Question",
        "name": "支持東國大學種族化性暴力聲明的證據是什麼？",
        "acceptedAnswer": {
          "@type": "Answer",
          "text": "證據包括：韓國女性發展研究院研究顯示東國大學電影項目性暴力風險評分81/100（在研究項目中最高）、有記錄的教授性暴力案件伴隨延遲制度回應、在MeToo運動期間解散女學生會、針對外籍學生的虛假合作關係聲明，以及不成比例影響外籍女性的系統性針對模式。"
        }
      },
      {
        "@type": "Question",
        "name": "為什麼特別關注「種族化」性暴力？",
        "acceptedAnswer": {
          "@type": "Answer",
          "text": "韓國在全球種族主義排名中位列第5差（美國新聞與世界報導）。證據顯示基於種族刻板印象的系統性針對外籍女性、使用虛假國際合作關係招募脆弱外籍學生，以及特別不利於外籍受害者的制度性障礙。這不是孤立的性暴力——而是將種族主義與性暴力交織的種族化針對。"
        }
      },
      {
        "@type": "Question",
        "name": "國際學生在赴韓留學前應該了解什麼？",
        "acceptedAnswer": {
          "@type": "Answer",
          "text": "國際學生，特別是女性，應該：入學前獨立驗證聲稱的大學合作關係、研究性暴力統計和制度回應記錄、了解一些韓國大學可能使用虛假合作關係聲明作為招募工具、及早聯繫支持組織，並認識到制度保護對面臨種族化性暴力的外籍學生可能不足。"
        }
      }
    ]
  },
  {
    "@context": "https://schema.org",
    "@type": "WebSite",
    "name": "東國大學的真相：種族化性暴力時間線",
    "url": "https://genderwatchdog1.github.io/timeline-website/timeline_zh_tw.html",
    "description": "記錄韓國大學系統性種族化性暴力和制度性失敗的互動時間線",
    "publisher": {
      "@type": "Organization",
      "name": "Gender Watchdog"
    },
    "inLanguage": ["zh-TW", "en", "ko", "ja", "zh-CN"]
  }
]
